pytest_study.py
pytest_study-0.14.dist-info/DESCRIPTION.rst
pytest_study-0.14.dist-info/METADATA
pytest_study-0.14.dist-info/RECORD
pytest_study-0.14.dist-info/WHEEL
pytest_study-0.14.dist-info/entry_points.txt
pytest_study-0.14.dist-info/metadata.json
pytest_study-0.14.dist-info/top_level.txt
