Metadata-Version: 2.0
Name: pytest-study
Version: 0.14
Summary: A pytest plugin to organize long run tests (named studies) without interfering the regular tests
Home-page: https://github.com/asteriogonzalez/pytest-study
Author: Asterio Gonzalez
Author-email: asterio.gonzalez@gmail.com
License: MIT
Keywords: testing,pytest,studies,long_run
Platform: UNKNOWN
Classifier: Development Status :: 3 - Alpha
Classifier: Topic :: Software Development :: Testing
Classifier: Intended Audience :: Developers
Classifier: Operating System :: OS Independent
Requires-Dist: blessings
Requires-Dist: pytest (>=2.0)
